{"paths":{"0":["Image/MainScene",0],"3":["JSONData/AdvertConfig_WX",3],"4":["Image/btnAudio",1,1],"6":["Prefab/GoldIcon",4],"8":["Prefab/CartoonMan",4],"9":["Image/btnAudioMask",1,1],"12":["Image/man",2]},"types":["cc.SpriteAtlas","cc.SpriteFrame","cc.AnimationClip","cc.JsonAsset","cc.Prefab"],"uuids":["09RXhX9wRNY6Q9/d2W/iW+","113d2290d","1ce123381","2eY5JxwgBDs6/XjaLKALou","4cW9iDgrRNi4a3KXq/E4Ta","71VhFCTINJM6/Ky3oX9nBT","92quptYQRB3b4RYFvXXWZy","b4P/PCArtIdIH38t6mlw8Y","bdy7Xyqk5A8Z6ieArEBg4s","cf0HNU1n1Pi4ooTY52pK1m","deIJuGUOBCz4FshALRl8Ej","e8Ueib+qJEhL6mXAHdnwbi","f2mDu3aXdHpInkjjjfxivG","02delMVqdBD70a/HSD99FK","05JSQAAuROY6+TiOCqnyH8","11gWGZWGtHAYvQVbrGc5G2","24P8XuxlROr6O5IIjWUVZE","26eX2ZMVpGTopFnqGJ/v1N","29FYIk+N1GYaeWH/q1NxQO","2bcdVOsWhDAI/y/Be8GizX","2b7VHhoQxOFqAnjcdbFWBP","4bDkY0UaFPo7xGreGYmdxo","58xrD/kQFFZZ0l91Qiuukf","6dZBoB/RVFzo5VHIrTk2hT","72Rv6UuolIdbxbfzF4adhn","72k8vMNvhHiZZCEcWT/0Zu","7c+KgVQkZMCbWud8p1hj4R","833F6JazxKwaK2ylq2oXy7","8ebabhPdNPuqfMoIMMj0d8","9fChK5bxtLdqwWywjRy1uw","a2MjXRFdtLlYQ5ouAFv/+R","b5Yd9vnIhG76PyROvN9/Jv","babnSY1ttKsr2SJ0AB2Omh","beAsD2n7lNjLpOuBz5obZs","ddhK60ZE1BIISSMr3HXYkf","e97GVMl6JHh5Ml5qEDdSGa","ecpdLyjvZBwrvm+cedCcQy","ed2Ba6BOxHra2X9XYrl2Ni","f0BIwQ8D5Ml7nTNQbh1YlS","f7L81xRzdD+p/PurOVioZj","fbHNgVUplADo8rzbA1G8pR","fbsfsbh+BPL7d3s6C46i8C"],"scenes":{"db://assets/MainScene/MainScene.fire":10},"redirect":[13,0,36,0],"deps":["internal"],"packs":{"03d68588d":[6,30],"059abc466":[14,17,19,21,23,25,26,27,29,31,32,33,34,37,41],"0a425205e":[8,12],"0a9bf04e3":[15,16,18,20,4,22,24,28,9,10,35,38,39,40],"0cebb6e50":[1,2,5,7,11]},"name":"MainScene","importBase":"import","nativeBase":"native","debug":false,"isZip":false,"encrypted":false,"versions":{"import":["03d68588d","4bb3d","059abc466","a896c",0,"1dbe0","0a425205e","10e5b","0a9bf04e3","f6ecb","0cebb6e50","72a64",3,"72992"],"native":[1,"5e5c1",2,"e89fa",5,"c06a9",7,"83fcc",11,"90cf4"]}}